{
  "name": "Power",
  "status": "experimental",
  "shortId": "power",
  "camelName": "power",
  "shortName": "power",
  "extends": [
    "_base"
  ],
  "notes": {
    "short": "A power-provider service."
  },
  "classIdentifier": 530893146,
  "enums": {},
  "packets": [
    {
      "kind": "ro",
      "name": "status_code",
      "identifier": 259,
      "description": "Reports the current state or error status of the device. ``code`` is a standardized value from \nthe JACDAC error codes. ``vendor_code`` is any vendor specific error code describing the device\nstate. This report is typically not queried, when a device has an error, it will typically\nadd this report in frame along with the anounce packet.",
      "fields": [
        {
          "name": "code",
          "unit": "",
          "type": "u16",
          "storage": 2,
          "isSimpleType": true
        },
        {
          "name": "vendor_code",
          "unit": "",
          "type": "u16",
          "storage": 2,
          "isSimpleType": true
        }
      ],
      "optional": true,
      "identifierName": "status_code",
      "packFormat": "u16 u16",
      "derived": "_base"
    },
    {
      "kind": "rw",
      "name": "enabled",
      "identifier": 1,
      "description": "Turn the power to the bus on/off.",
      "fields": [
        {
          "name": "_",
          "unit": "",
          "type": "bool",
          "storage": 1,
          "defaultValue": 1
        }
      ],
      "identifierName": "intensity",
      "packFormat": "u8"
    },
    {
      "kind": "rw",
      "name": "max_power",
      "identifier": 7,
      "description": "Limit the power provided by the service. The actual maximum limit will depend on hardware.\nThis field may be read-only in some implementations - you should read it back after setting.",
      "fields": [
        {
          "name": "_",
          "unit": "mA",
          "type": "u16",
          "storage": 2,
          "isSimpleType": true,
          "defaultValue": 500,
          "typicalMax": 500,
          "typicalMin": 0
        }
      ],
      "identifierName": "max_power",
      "packFormat": "u16"
    },
    {
      "kind": "ro",
      "name": "overload",
      "identifier": 385,
      "description": "Indicates whether the power has been shut down due to overdraw.",
      "fields": [
        {
          "name": "_",
          "unit": "",
          "type": "bool",
          "storage": 1
        }
      ],
      "packFormat": "u8"
    },
    {
      "kind": "ro",
      "name": "current_draw",
      "identifier": 257,
      "description": "Present current draw from the bus.",
      "fields": [
        {
          "name": "_",
          "unit": "mA",
          "type": "u16",
          "storage": 2,
          "isSimpleType": true
        }
      ],
      "identifierName": "reading",
      "packFormat": "u16"
    },
    {
      "kind": "ro",
      "name": "battery_voltage",
      "identifier": 384,
      "description": "Voltage on input.",
      "fields": [
        {
          "name": "_",
          "unit": "mV",
          "type": "u16",
          "storage": 2,
          "isSimpleType": true,
          "typicalMin": 4500,
          "typicalMax": 5500
        }
      ],
      "packFormat": "u16"
    },
    {
      "kind": "ro",
      "name": "battery_charge",
      "identifier": 386,
      "description": "Fraction of charge in the battery.",
      "fields": [
        {
          "name": "_",
          "unit": "/",
          "shift": 16,
          "type": "u16",
          "storage": 2,
          "isSimpleType": true
        }
      ],
      "optional": true,
      "packFormat": "u16"
    },
    {
      "kind": "const",
      "name": "battery_capacity",
      "identifier": 387,
      "description": "Energy that can be delivered to the bus when battery is fully charged.\nThis excludes conversion overheads if any.",
      "fields": [
        {
          "name": "_",
          "unit": "mWh",
          "type": "u32",
          "storage": 4,
          "isSimpleType": true
        }
      ],
      "optional": true,
      "packFormat": "u32"
    },
    {
      "kind": "rw",
      "name": "keep_on_pulse_duration",
      "identifier": 128,
      "description": "Many USB power packs need current to be drawn from time to time to prevent shutdown.\nThis regulates how often and for how long such current is drawn.\nTypically a 1/8W 22 ohm resistor is used as load. This limits the duty cycle to 10%.",
      "fields": [
        {
          "name": "_",
          "unit": "ms",
          "type": "u16",
          "storage": 2,
          "isSimpleType": true,
          "defaultValue": 600
        }
      ],
      "packFormat": "u16"
    },
    {
      "kind": "rw",
      "name": "keep_on_pulse_period",
      "identifier": 129,
      "description": "Many USB power packs need current to be drawn from time to time to prevent shutdown.\nThis regulates how often and for how long such current is drawn.\nTypically a 1/8W 22 ohm resistor is used as load. This limits the duty cycle to 10%.",
      "fields": [
        {
          "name": "_",
          "unit": "ms",
          "type": "u16",
          "storage": 2,
          "isSimpleType": true,
          "defaultValue": 20000
        }
      ],
      "packFormat": "u16"
    }
  ]
}